{
  "version": "1.0.0",
  "description": "Berry Platform — DX Terminal Registry",
  "nodes": [

    {
      "nodeId": "metrics-base-01",
      "label": "Base Metrics",
      "type": "metrics-node",
      "schedule": "*/2 * * * *",
      "meta": {
        "chain": "base",
        "rpc": "https://mainnet.base.org"
      }
    },
    {
      "nodeId": "metrics-eth-01",
      "label": "Ethereum Metrics",
      "type": "metrics-node",
      "schedule": "*/2 * * * *",
      "meta": {
        "chain": "ethereum",
        "rpc": "https://eth.llamarpc.com"
      }
    },
    {
      "nodeId": "metrics-arb-01",
      "label": "Arbitrum Metrics",
      "type": "metrics-node",
      "schedule": "*/2 * * * *",
      "meta": {
        "chain": "arbitrum",
        "rpc": "https://arb1.arbitrum.io/rpc"
      }
    },
    {
      "nodeId": "metrics-poly-01",
      "label": "Polygon Metrics",
      "type": "metrics-node",
      "schedule": "*/2 * * * *",
      "meta": {
        "chain": "polygon",
        "rpc": "https://polygon-rpc.com"
      }
    },

    {
      "nodeId": "heartbeat-core-01",
      "label": "Core Engine Heartbeat",
      "type": "heartbeat",
      "schedule": "*/1 * * * *",
      "meta": {
        "chain": "base",
        "rpc": "https://mainnet.base.org"
      }
    },

    {
      "nodeId": "heartbeat-base-contract-01",
      "label": "Base Contract Heartbeat",
      "type": "heartbeat",
      "schedule": "*/2 * * * *",
      "meta": {
        "chain": "base",
        "rpc": "https://mainnet.base.org",
        "contract": "0xa25e0Af7Dd580fcF7121FD7BE95c3f3beE258e8f"
      }
    },
    {
      "nodeId": "heartbeat-eth-wallet-01",
      "label": "Ethereum Wallet Heartbeat",
      "type": "heartbeat",
      "schedule": "*/2 * * * *",
      "meta": {
        "chain": "ethereum",
        "rpc": "https://eth.llamarpc.com",
        "wallet": "0x08010c81e0095fD9b2D90f73E71774dBee174C8b"
      }
    },
    {
  "nodeId": "heartbeat-arb-contract-01",
  "label": "Arbitrum Contract Heartbeat",
  "type": "heartbeat",
  "schedule": "*/3 * * * *",
  "meta": {
    "chain": "arbitrum",
    "rpc": "https://arb1.arbitrum.io/rpc",
    "contract": "0x2c1D26c24b0dd9b9cc365435CF4De2317319F0"
  }
},
    {
      "nodeId": "heartbeat-poly-wallet-01",
      "label": "Polygon Wallet Heartbeat",
      "type": "heartbeat",
      "schedule": "*/3 * * * *",
      "meta": {
        "chain": "polygon",
        "rpc": "https://polygon-rpc.com",
        "wallet": "0xCa686A22cCa55740E853a8c28046E4bF9c56D0A2"
      }
    },

    {
      "nodeId": "scanner-base-contract-01",
      "label": "Base Contract Scanner",
      "type": "scanner-node",
      "schedule": "*/3 * * * *",
      "meta": {
        "chain": "base",
        "rpc": "https://mainnet.base.org",
        "contract": "0xa25e0Af7Dd580fcF7121FD7BE95c3f3beE258e8f"
      }
    },
    {
      "nodeId": "scanner-eth-wallet-01",
      "label": "Ethereum Wallet Scanner",
      "type": "scanner-node",
      "schedule": "*/3 * * * *",
      "meta": {
        "chain": "ethereum",
        "rpc": "https://eth.llamarpc.com",
        "wallet": "0x08010c81e0095fD9b2D90f73E71774dBee174C8b"
      }
    },
    {
      "nodeId": "scanner-arb-events-01",
      "label": "Arbitrum Event Scanner",
      "type": "scanner-node",
      "schedule": "*/4 * * * *",
      "meta": {
        "chain": "arbitrum",
        "rpc": "https://arb1.arbitrum.io/rpc",
        "contract": "0x2c1D26c24b0dd9b9cc365435CF4De2317319F0"
      }
    },
  {
  "nodeId": "scanner-poly-multi-01",
  "label": "Polygon Wallet Scanner",
  "type": "scanner-node",
  "schedule": "*/4 * * * *",
  "meta": {
    "chain": "polygon",
    "rpc": "https://polygon-rpc.com",
    "wallet": "0xCa686A22cCa55740E853a8c28046E4bF9c56D0A2"
  }
},
    {
      "nodeId": "dex-base-pool-01",
      "label": "Base DEX Pool",
      "type": "dex-node",
      "schedule": "*/3 * * * *",
      "meta": {
        "chain": "base",
        "rpc": "https://mainnet.base.org",
        "pool": "<BASE_POOL_ADDRESS>",
        "token0": "<BASE_TOKEN0>",
        "token1": "<BASE_TOKEN1>"
      }
    },
    {
      "nodeId": "dex-eth-pool-01",
      "label": "Ethereum DEX Pool",
      "type": "dex-node",
      "schedule": "*/3 * * * *",
      "meta": {
        "chain": "ethereum",
        "rpc": "https://eth.llamarpc.com",
        "pool": "<ETH_POOL_ADDRESS>",
        "token0": "<ETH_TOKEN0>",
        "token1": "<ETH_TOKEN1>"
      }
    },
    {
      "nodeId": "dex-arb-pool-01",
      "label": "Arbitrum DEX Pool",
      "type": "dex-node",
      "schedule": "*/4 * * * *",
      "meta": {
        "chain": "arbitrum",
        "rpc": "https://arb1.arbitrum.io/rpc",
        "pool": "<ARB_POOL_ADDRESS>",
        "token0": "<ARB_TOKEN0>",
        "token1": "<ARB_TOKEN1>"
      }
    },
    {
      "nodeId": "dex-poly-pool-01",
      "label": "Polygon DEX Pool",
      "type": "dex-node",
      "schedule": "*/4 * * * *",
      "meta": {
        "chain": "polygon",
        "rpc": "https://polygon-rpc.com",
        "pool": "<POLY_POOL_ADDRESS>",
        "token0": "<POLY_TOKEN0>",
        "token1": "<POLY_TOKEN1>"
      }
    },

     {
       "nodeId": "cert-latest-01",
       "label": "Cert Latest Artefact",
       "type": "cert-node",
       "schedule": "*/5 * * * *",
       "meta": {
        "artefactPath": "./output/",
 "ledgerFile": "./cert-ledger/cert-ledger.json",
    "notes": "Primary cert node-hashes latest artefact and updates ledger"
  }
},
   {
  "nodeId": "cert-latest-02",
  "label": "Cert Latest Artefact (Secondary)",
  "type": "cert-node",
  "schedule": "*/7 * * * *",
  "meta": {
    "artefactPath": "./output/",
    "ledgerFile": "./cert-ledger/cert-ledger.json",
    "notes": "Secondary cert node — redundancy pass"
  }
},
    {
      "nodeId": "orchestrator-summary-01",
      "label": "Global Orchestrator Summary",
      "type": "orchestrator",
      "schedule": "*/5 * * * *",
      "meta": {
        "notes": "Aggregates all node outputs into a global summary"
      }
    },
    {
      "nodeId": "orchestrator-healthmap-01",
      "label": "Health Map Orchestrator",
      "type": "orchestrator",
      "schedule": "*/10 * * * *",
      "meta": {
        "notes": "Secondary orchestrator for health mapping"
      }
    },

    {
      "nodeId": "movement-core-01",
      "label": "Core Movement Status",
      "type": "movement",
      "schedule": "*/10 * * * *",
      "meta": {
        "notes": "Reads artefacts + certs to derive movement status"
      }
    },
    {
      "nodeId": "movement-relics-01",
      "label": "Relic Lineage Movement Node",
      "type": "movement",
      "schedule": "*/15 * * * *",
      "meta": {
        "notes": "Reserved for relic-lineage.json integration"
      }
    }

  ]
}
