{
  "nodeId": "metrics-base-01",
  "type": "metrics-node",
  "label": "Base Metrics",
  "timestamp": "2026-01-31T14:17:35.040Z",
  "status": "healthy",
  "data": {
    "nodeId": "metrics-base-01",
    "label": "Base Metrics",
    "type": "metrics-node",
    "timestamp": "2026-01-31T14:17:35.040Z",
    "chain": "base",
    "metrics": {
      "rpcLatencyMs": 491.0451499996707,
      "latestBlock": 41539854,
      "gasPriceWei": "0x5600dc5",
      "filesystem": {
        "outputDirExists": true,
        "outputFileCount": 1983
      }
    },
    "status": "healthy"
  }
}