{
  "nodeId": "metrics-base-01",
  "type": "metrics-node",
  "label": "Base Metrics",
  "timestamp": "2026-01-31T16:37:41.187Z",
  "status": "healthy",
  "data": {
    "nodeId": "metrics-base-01",
    "label": "Base Metrics",
    "type": "metrics-node",
    "timestamp": "2026-01-31T16:37:41.187Z",
    "chain": "base",
    "metrics": {
      "rpcLatencyMs": 426.22559499926865,
      "latestBlock": 41544057,
      "gasPriceWei": "0x190d95e",
      "filesystem": {
        "outputDirExists": true,
        "outputFileCount": 3030
      }
    },
    "status": "healthy"
  }
}